patchwork/__init__.py
patchwork/__main__.py
patchwork/app.py
patchwork/logger.py
patchwork/managed_files.py
patchwork/step.py
patchwork/common/constants.py
patchwork/common/server.py
patchwork/common/client/llm/__init__.py
patchwork/common/client/llm/aio.py
patchwork/common/client/llm/anthropic.py
patchwork/common/client/llm/google.py
patchwork/common/client/llm/openai_.py
patchwork/common/client/llm/protocol.py
patchwork/common/client/llm/utils.py
patchwork/common/context_strategy/__init__.py
patchwork/common/context_strategy/context_strategies.py
patchwork/common/context_strategy/cpp.py
patchwork/common/context_strategy/generic.py
patchwork/common/context_strategy/java.py
patchwork/common/context_strategy/javascript.py
patchwork/common/context_strategy/kotlin.py
patchwork/common/context_strategy/languages.py
patchwork/common/context_strategy/position.py
patchwork/common/context_strategy/protocol.py
patchwork/common/context_strategy/python.py
patchwork/common/utils/__init__.py
patchwork/common/utils/dependency.py
patchwork/common/utils/filter_paths.py
patchwork/common/utils/input_parsing.py
patchwork/common/utils/progress_bar.py
patchwork/common/utils/step_typing.py
patchwork/common/utils/user_config.py
patchwork/common/utils/utils.py
patchwork/patchflows/__init__.py
patchwork/patchflows/AutoFix/AutoFix.py
patchwork/patchflows/DependencyUpgrade/DependencyUpgrade.py
patchwork/patchflows/GenerateDocstring/GenerateDocstring.py
patchwork/patchflows/GenerateDocstring/__init__.py
patchwork/patchflows/GenerateREADME/GenerateREADME.py
patchwork/patchflows/GenerateUnitTests/GenerateUnitTests.py
patchwork/patchflows/GenerateUnitTests/__init__.py
patchwork/patchflows/PRReview/PRReview.py
patchwork/patchflows/PRReview/__init__.py
patchwork/patchflows/ResolveIssue/ResolveIssue.py
patchwork/patchflows/ResolveIssue/__init__.py
patchwork/steps/__init__.py
patchwork/steps/AnalyzeImpact/AnalyzeImpact.py
patchwork/steps/AnalyzeImpact/__init__.py
york_patched-1.0.2.dist-info/METADATA
york_patched-1.0.2.dist-info/WHEEL
york_patched-1.0.2.dist-info/top_level.txt
york_patched-1.0.2.dist-info/RECORD
